pyglet_ffmpeg2/__init__.py
pyglet_ffmpeg2/loader.py
pyglet_ffmpeg2/MacOS/libavcodec.58.dylib
pyglet_ffmpeg2/MacOS/libavdevice.58.dylib
pyglet_ffmpeg2/MacOS/libavfilter.7.dylib
pyglet_ffmpeg2/MacOS/libavformat.58.dylib
pyglet_ffmpeg2/MacOS/libavutil.56.dylib
pyglet_ffmpeg2/MacOS/libpostproc.55.dylib
pyglet_ffmpeg2/MacOS/libswresample.3.dylib
pyglet_ffmpeg2/MacOS/libswscale.5.dylib
pyglet_ffmpeg2-0.1.14.dist-info/LICENSE
pyglet_ffmpeg2-0.1.14.dist-info/METADATA
pyglet_ffmpeg2-0.1.14.dist-info/NOTICE.txt
pyglet_ffmpeg2-0.1.14.dist-info/WHEEL
pyglet_ffmpeg2-0.1.14.dist-info/top_level.txt
pyglet_ffmpeg2-0.1.14.dist-info/RECORD
